curator/__init__.py
curator/_version.py
curator/actions.py
curator/cli.py
curator/config_utils.py
curator/curator_cli.py
curator/exceptions.py
curator/indexlist.py
curator/logtools.py
curator/repomgrcli.py
curator/singletons.py
curator/snapshotlist.py
curator/utils.py
curator/cli_singletons/__init__.py
curator/cli_singletons/alias.py
curator/cli_singletons/allocation.py
curator/cli_singletons/close.py
curator/cli_singletons/delete.py
curator/cli_singletons/forcemerge.py
curator/cli_singletons/freeze.py
curator/cli_singletons/object_class.py
curator/cli_singletons/open_indices.py
curator/cli_singletons/replicas.py
curator/cli_singletons/restore.py
curator/cli_singletons/rollover.py
curator/cli_singletons/show.py
curator/cli_singletons/shrink.py
curator/cli_singletons/snapshot.py
curator/cli_singletons/unfreeze.py
curator/cli_singletons/utils.py
curator/defaults/__init__.py
curator/defaults/client_defaults.py
curator/defaults/filter_elements.py
curator/defaults/filtertypes.py
curator/defaults/option_defaults.py
curator/defaults/settings.py
curator/validators/__init__.py
curator/validators/actions.py
curator/validators/config_file.py
curator/validators/filters.py
curator/validators/options.py
curator/validators/schemacheck.py
curator_opensearch-0.0.12.dist-info/LICENSE
curator_opensearch-0.0.12.dist-info/METADATA
curator_opensearch-0.0.12.dist-info/NOTICE
curator_opensearch-0.0.12.dist-info/WHEEL
curator_opensearch-0.0.12.dist-info/entry_points.txt
curator_opensearch-0.0.12.dist-info/top_level.txt
curator_opensearch-0.0.12.dist-info/RECORD
