Metadata-Version: 2.1
Name: curator-opensearch
Version: 0.0.12
Summary: Tending your Elasticsearch indices
Home-page: https://github.com/uzhinskiy/curator-opensearch
Download-URL: https://github.com/uzhinskiy/curator-opensearch/releases/tag/0.0.12
Author: Uzhinsky
Author-email: lspci@mail.ru
License: Apache License, Version 2.0
Keywords: elasticsearch time-series indexed index-expiry
Classifier: Intended Audience :: Developers
Classifier: Intended Audience :: System Administrators
Classifier: License :: OSI Approved :: Apache Software License
Classifier: Operating System :: OS Independent
Classifier: Programming Language :: Python
Classifier: Programming Language :: Python :: 3.7
Classifier: Programming Language :: Python :: 3.8
Classifier: Programming Language :: Python :: 3.9
License-File: LICENSE
License-File: NOTICE
Requires-Dist: opensearch-py (>=1.0.0)
Requires-Dist: urllib3 (<2,>=1.26.5)
Requires-Dist: requests (>=2.26.0)
Requires-Dist: boto3 (>=1.18.18)
Requires-Dist: requests-aws4auth (>=1.1.1)
Requires-Dist: click (<8.0,>=7.0)
Requires-Dist: pyyaml (>=5.4.1)
Requires-Dist: voluptuous (>=0.12.1)
Requires-Dist: certifi (>=2021.5.30)
Requires-Dist: six (>=1.16.0)
